yasgg
