Metadata-Version: 1.0
Name: YASGG
Version: 0.1.3
Summary: YASGG is a static gallery generator with optional encryption support written in python.
Home-page: https://github.com/nomnomnom/yasgg
Author: nomnomnom
Author-email: nomnomnom@secure-mail.cc
License: Beer
Platform: UNKNOWN
